fkeycapture/__init__.py
fkeycapture/__init__.pyi
fkeycapture/py.typed
fkeycapture-1.3.0.dist-info/LICENSE
fkeycapture-1.3.0.dist-info/METADATA
fkeycapture-1.3.0.dist-info/WHEEL
fkeycapture-1.3.0.dist-info/RECORD
