Metadata-Version: 2.3
Name: fkeycapture
Version: 1.3.0
Summary: A way to capture keystrokes
License: MIT
Author: Firepup650
Author-email: firepyp650@gmail.com
Requires-Python: >=3.8,<4.0
Classifier: Development Status :: 5 - Production/Stable
Classifier: Environment :: Console
Classifier: Intended Audience :: Developers
Classifier: License :: OSI Approved :: MIT License
Classifier: Natural Language :: English
Classifier: Operating System :: OS Independent
Classifier: Programming Language :: Python :: 3
Classifier: Programming Language :: Python :: 3.8
Classifier: Programming Language :: Python :: 3.9
Classifier: Programming Language :: Python :: 3.10
Classifier: Programming Language :: Python :: 3.11
Classifier: Programming Language :: Python :: 3.12
Classifier: Programming Language :: Python :: 3.13
Project-URL: Bug Tracker, https://github.com/F1repup650/fkeycapture/issues
Project-URL: Repository, https://github.com/F1repup650/fkeycapture
Project-URL: Replit, https://replit.com/@Firepup650/fkeycapture
